vcztools/__init__.py
vcztools/__main__.py
vcztools/_vcztools.cpython-311-x86_64-linux-gnu.so
vcztools/_vcztoolsmodule.c
vcztools/_version.py
vcztools/cli.py
vcztools/constants.py
vcztools/filter.py
vcztools/plink.py
vcztools/provenance.py
vcztools/query.py
vcztools/regions.py
vcztools/retrieval.py
vcztools/samples.py
vcztools/stats.py
vcztools/utils.py
vcztools/vcf_writer.py
vcztools-0.1.0.dist-info/METADATA
vcztools-0.1.0.dist-info/WHEEL
vcztools-0.1.0.dist-info/entry_points.txt
vcztools-0.1.0.dist-info/top_level.txt
vcztools-0.1.0.dist-info/RECORD
vcztools-0.1.0.dist-info/licenses/LICENSE
