Metadata-Version: 2.4
Name: vcztools
Version: 0.1.0
Summary: Implementation of bcftools for VCF Zarr
Author-email: sgkit Developers <project@sgkit.dev>
License:                                  Apache License
Project-URL: repository, https://github.com/sgkit-dev/vcztools
Classifier: Development Status :: 4 - Beta
Classifier: License :: OSI Approved :: Apache Software License
Classifier: Operating System :: POSIX
Classifier: Operating System :: POSIX :: Linux
Classifier: Operating System :: MacOS
Classifier: Operating System :: MacOS :: MacOS X
Classifier: Intended Audience :: Science/Research
Classifier: Programming Language :: Python
Classifier: Programming Language :: Python :: 3
Classifier: Programming Language :: Python :: 3.10
Classifier: Programming Language :: Python :: 3.11
Classifier: Programming Language :: Python :: 3.12
Classifier: Topic :: Scientific/Engineering
Requires-Python: >=3.10
License-File: LICENSE
Requires-Dist: numpy>=1.23.5
Requires-Dist: zarr<3,>=2.17
Requires-Dist: click>=8.2.0
Requires-Dist: pyranges!=0.1.3
Requires-Dist: pyparsing>=3
Provides-Extra: dev
Requires-Dist: bio2zarr; extra == "dev"
Requires-Dist: cyvcf2; extra == "dev"
Requires-Dist: pytest; extra == "dev"
Requires-Dist: pytest-cov; extra == "dev"
Requires-Dist: msprime; extra == "dev"
Requires-Dist: sgkit; extra == "dev"
Dynamic: license-file
